DockerJianmingJiaocheng/README.md
DockerJianmingJiaocheng/__init__.py
DockerJianmingJiaocheng/__main__.py
DockerJianmingJiaocheng/file.epub
DockerJianmingJiaocheng/index.html
DockerJianmingJiaocheng/css/__init__.py
DockerJianmingJiaocheng/css/annotations.css
DockerJianmingJiaocheng/css/main.css
DockerJianmingJiaocheng/css/normalize.css
DockerJianmingJiaocheng/css/popup.css
DockerJianmingJiaocheng/font/__init__.py
DockerJianmingJiaocheng/font/fontello.eot
DockerJianmingJiaocheng/font/fontello.svg
DockerJianmingJiaocheng/font/fontello.ttf
DockerJianmingJiaocheng/font/fontello.woff
DockerJianmingJiaocheng/img/__init__.py
DockerJianmingJiaocheng/img/annotator-glyph-sprite.png
DockerJianmingJiaocheng/img/annotator-icon-sprite.png
DockerJianmingJiaocheng/img/apple-touch-icon.png
DockerJianmingJiaocheng/img/cancelfullscreen.png
DockerJianmingJiaocheng/img/close.png
DockerJianmingJiaocheng/img/fullscreen.png
DockerJianmingJiaocheng/img/loader.gif
DockerJianmingJiaocheng/img/menu-icon.png
DockerJianmingJiaocheng/img/save.png
DockerJianmingJiaocheng/img/saved.png
DockerJianmingJiaocheng/img/settings-s.png
DockerJianmingJiaocheng/img/settings.png
DockerJianmingJiaocheng/img/star.png
DockerJianmingJiaocheng/js/__init__.py
DockerJianmingJiaocheng/js/epub.js
DockerJianmingJiaocheng/js/epub.min.js
DockerJianmingJiaocheng/js/epub.min.map
DockerJianmingJiaocheng/js/hooks.min.js
DockerJianmingJiaocheng/js/hooks.min.map
DockerJianmingJiaocheng/js/reader.js
DockerJianmingJiaocheng/js/reader.js.map
DockerJianmingJiaocheng/js/reader.min.js
DockerJianmingJiaocheng/js/reader.min.map
DockerJianmingJiaocheng/js/hooks/__init__.py
DockerJianmingJiaocheng/js/hooks/extensions/__init__.py
DockerJianmingJiaocheng/js/hooks/extensions/highlight.js
DockerJianmingJiaocheng/js/libs/__init__.py
DockerJianmingJiaocheng/js/libs/jquery.min.js
DockerJianmingJiaocheng/js/libs/localforage.min.js
DockerJianmingJiaocheng/js/libs/screenfull.js
DockerJianmingJiaocheng/js/libs/screenfull.min.js
docker_jianming_jiaocheng-2024.3.3.0.dist-info/METADATA
docker_jianming_jiaocheng-2024.3.3.0.dist-info/WHEEL
docker_jianming_jiaocheng-2024.3.3.0.dist-info/entry_points.txt
docker_jianming_jiaocheng-2024.3.3.0.dist-info/top_level.txt
docker_jianming_jiaocheng-2024.3.3.0.dist-info/RECORD
